feed_gov_back-0.3.dist-info/DESCRIPTION.rst
feed_gov_back-0.3.dist-info/METADATA
feed_gov_back-0.3.dist-info/RECORD
feed_gov_back-0.3.dist-info/WHEEL
feed_gov_back-0.3.dist-info/metadata.json
feed_gov_back-0.3.dist-info/top_level.txt
feedback/__init__.py
feedback/admin.py
feedback/apps.py
feedback/base.py
feedback/exceptions.py
feedback/models.py
feedback/urls.py
feedback/utils.py
feedback/version.py
feedback/views.py
feedback/migrations/0001_initial.py
feedback/migrations/0002_auto_20190109_1254.py
feedback/migrations/__init__.py
feedback/services/__init__.py
feedback/services/api.py
feedback/services/base.py
feedback/services/exceptions.py
feedback/services/urls.py
feedback/templates/complete.html
feedback/templates/feedback_form.html
feedback/templates/elements/base.html
feedback/templates/elements/scale.html
feedback/templates/elements/text.html
feedback/templates/elements/textarea.html
feedback/templatetags/__init__.py
feedback/templatetags/feedback_element.py
feedback/templatetags/feedback_form.py
tests/__init__.py
tests/base.py
tests/test_api.py
tests/test_feedback.py
tests/test_settings.py
