Metadata-Version: 2.0
Name: feed-gov-back
Version: 0.3
Summary: A small framework for API enabled customisable feedback forms
Home-page: https://github.com/uktrade/feed-gov-back
Author: Harel Malka
Author-email: harel@harelmalka.com
License: MIT
Platform: UNKNOWN
Classifier: Environment :: Web Environment
Classifier: Framework :: Django
Classifier: Framework :: Django :: 2.0
Classifier: Intended Audience :: Developers
Classifier: Operating System :: OS Independent
Classifier: Programming Language :: Python
Classifier: Programming Language :: Python :: 3.6
Classifier: Programming Language :: Python :: 3.7
Requires-Dist: psycopg2-binary
Requires-Dist: Django
Requires-Dist: djangorestframework
